[{"doc":"The applicaton environment","format":["production","development","test"],"default":"development","env":"NODE_ENV","_key":"env"},{"doc":"The port to bind","default":0,"env":"PORT","_key":"port"},{"doc":"GitHub access token","default":null,"env":"GITHUB_TOKEN","_key":"githubToken"},{"doc":"Akismet site","default":null,"env":"AKISMET_SITE","_key":"akistmet.site"},{"doc":"Akismet API key","default":null,"env":"AKISMET_API_KEY","_key":"akistmet.apiKey"},{"doc":"Universal Analytics Analytics account ID","default":null,"env":"UA_TRACKING_ID","_key":"analytics.uaTrackingId"},{"doc":"RSA private key","default":null,"env":"RSA_PRIVATE_KEY","_key":"rsaPrivateKey"},{"doc":"Email service API key","default":null,"env":"EMAIL_API_KEY","_key":"email.apiKey"},{"doc":"Email service domain","default":"staticman.net","env":"EMAIL_DOMAIN","_key":"email.domain"},{"doc":"Email address to send notifications as","default":"noreply@staticman.net","env":"EMAIL_FROM","_key":"email.fromAddress"}]